dj_rest_auth/__init__.py
dj_rest_auth/__version__.py
dj_rest_auth/admin.py
dj_rest_auth/app_settings.py
dj_rest_auth/forms.py
dj_rest_auth/jwt_auth.py
dj_rest_auth/models.py
dj_rest_auth/serializers.py
dj_rest_auth/social_serializers.py
dj_rest_auth/urls.py
dj_rest_auth/utils.py
dj_rest_auth/views.py
dj_rest_auth/locale/cs/LC_MESSAGES/django.mo
dj_rest_auth/locale/cs/LC_MESSAGES/django.po
dj_rest_auth/locale/de/LC_MESSAGES/django.mo
dj_rest_auth/locale/de/LC_MESSAGES/django.po
dj_rest_auth/locale/es/LC_MESSAGES/django.mo
dj_rest_auth/locale/es/LC_MESSAGES/django.po
dj_rest_auth/locale/fa/LC_MESSAGES/django.po
dj_rest_auth/locale/fr/LC_MESSAGES/django.mo
dj_rest_auth/locale/fr/LC_MESSAGES/django.po
dj_rest_auth/locale/hr/LC_MESSAGES/django.po
dj_rest_auth/locale/it/LC_MESSAGES/django.mo
dj_rest_auth/locale/it/LC_MESSAGES/django.po
dj_rest_auth/locale/ja/LC_MESSAGES/django.po
dj_rest_auth/locale/ko/LC_MESSAGES/django.mo
dj_rest_auth/locale/ko/LC_MESSAGES/django.po
dj_rest_auth/locale/nl/LC_MESSAGES/django.mo
dj_rest_auth/locale/nl/LC_MESSAGES/django.po
dj_rest_auth/locale/pl/LC_MESSAGES/django.mo
dj_rest_auth/locale/pl/LC_MESSAGES/django.po
dj_rest_auth/locale/pt_BR/LC_MESSAGES/django.mo
dj_rest_auth/locale/pt_BR/LC_MESSAGES/django.po
dj_rest_auth/locale/ro/LC_MESSAGES/django.mo
dj_rest_auth/locale/ro/LC_MESSAGES/django.po
dj_rest_auth/locale/ru/LC_MESSAGES/django.mo
dj_rest_auth/locale/ru/LC_MESSAGES/django.po
dj_rest_auth/locale/sv/LC_MESSAGES/django.mo
dj_rest_auth/locale/sv/LC_MESSAGES/django.po
dj_rest_auth/locale/tr/LC_MESSAGES/django.po
dj_rest_auth/locale/uk/LC_MESSAGES/django.po
dj_rest_auth/locale/zh_Hans/LC_MESSAGES/django.mo
dj_rest_auth/locale/zh_Hans/LC_MESSAGES/django.po
dj_rest_auth/locale/zh_Hant/LC_MESSAGES/django.mo
dj_rest_auth/locale/zh_Hant/LC_MESSAGES/django.po
dj_rest_auth/registration/__init__.py
dj_rest_auth/registration/app_settings.py
dj_rest_auth/registration/serializers.py
dj_rest_auth/registration/urls.py
dj_rest_auth_social-2.2.4.dist-info/LICENSE
dj_rest_auth_social-2.2.4.dist-info/METADATA
dj_rest_auth_social-2.2.4.dist-info/WHEEL
dj_rest_auth_social-2.2.4.dist-info/top_level.txt
dj_rest_auth_social-2.2.4.dist-info/RECORD
