Metadata-Version: 2.1
Name: dj-rest-auth-social
Version: 2.2.4
Summary: Authentication and Registration in Django Rest Framework
Home-page: https://github.com/robertwt7/dj-rest-auth-social
Author: robertwt7
Author-email: robert@sharkware.org
License: MIT
Keywords: django rest auth registration rest-framework django-registration api
Platform: UNKNOWN
Classifier: Framework :: Django
Classifier: Intended Audience :: Developers
Classifier: Intended Audience :: System Administrators
Classifier: Operating System :: OS Independent
Classifier: Topic :: Software Development
Requires-Python: >=3.5
Provides-Extra: with_social
License-File: LICENSE
